miketest/__init__.py
miketest/test.py
miketest-0.0.3.dist-info/METADATA
miketest-0.0.3.dist-info/WHEEL
miketest-0.0.3.dist-info/top_level.txt
miketest-0.0.3.dist-info/RECORD
