Metadata-Version: 2.1
Name: miketest
Version: 0.0.3
Summary: pypi test
Home-page: UNKNOWN
Author: mike
Author-email: mike@gmai.com
License: MIT`
Platform: UNKNOWN
Classifier: Programming Language :: Python :: 3
Classifier: License :: OSI Approved :: MIT License
Classifier: Operating System :: OS Independent
